pyupb/__init__.py
pyupb-0.0.1.dist-info/METADATA
pyupb-0.0.1.dist-info/WHEEL
pyupb-0.0.1.dist-info/licenses/LICENSE
pyupb-0.0.1.dist-info/RECORD
